panta_rhei/__init__.py
panta_rhei/boundary.py
panta_rhei/computers.py
panta_rhei/config.py
panta_rhei/domain.py
panta_rhei/elements.py
panta_rhei/fenicsstorage.py
panta_rhei/forms.py
panta_rhei/interpolator.py
panta_rhei/io_utils.py
panta_rhei/meshprocessing.py
panta_rhei/mms.py
panta_rhei/projectors.py
panta_rhei/solvers.py
panta_rhei/timekeeper.py
panta_rhei/utils.py
panta_rhei/_cli/__init__.py
panta_rhei/_cli/mesh_quality.py
panta_rhei/io/__init__.py
panta_rhei/io/timeseriesstorage.py
panta_rhei-0.7.0.dist-info/licenses/LICENSE
pantarei/__init__.py
panta_rhei-0.7.0.dist-info/METADATA
panta_rhei-0.7.0.dist-info/WHEEL
panta_rhei-0.7.0.dist-info/top_level.txt
panta_rhei-0.7.0.dist-info/RECORD
