Metadata-Version: 2.4
Name: panta-rhei
Version: 0.7.0
Summary: Miscellaneous fenics/dolfin utilities that are used in various projects.
Author-email: Jørgen Riseth <jnriseth@gmail.com>
License-Expression: MIT
Classifier: Programming Language :: Python :: 3
Requires-Python: >=3.10
License-File: LICENSE
Requires-Dist: loguru
Requires-Dist: sympy
Requires-Dist: matplotlib
Requires-Dist: meshio[all]
Requires-Dist: numpy
Requires-Dist: gmsh
Dynamic: license-file
